azure_ddns/__init__.py
azure_ddns/cli.py
azure_ddns/example-config.json
azure_ddns/setup.cfg
azure_ddns/setup.py
azure_ddns-0.0.3.dist-info/entry_points.txt
azure_ddns-0.0.3.dist-info/WHEEL
azure_ddns-0.0.3.dist-info/METADATA
azure_ddns-0.0.3.dist-info/RECORD
