Metadata-Version: 2.1
Name: azure-ddns
Version: 0.0.3
Summary: 
Home-page: https://github.com/tle06/azure-ddns
License: MIT
Author: tle06
Author-email: tle@tlnk.fr
Requires-Python: >=3.10,<4.0
Classifier: License :: OSI Approved :: MIT License
Classifier: Programming Language :: Python :: 3
Classifier: Programming Language :: Python :: 3.10
Requires-Dist: azure-identity (>=1.10.0,<2.0.0)
Requires-Dist: azure-mgmt-dns (>=8.0.0,<9.0.0)
Project-URL: Repository, https://github.com/tle06/azure-ddns
